{
  "category": "PEAK",
  "category_name": "Peak list file URI",
  "checksum": null,
  "checksum_source": null,
  "dataset_accession": "PXD000001",
  "file_accession": "ca2e3dea18950a328b7dc8303911961267a2c19058e67bfe49ab0d6784c3f62b",
  "file_name": "PRIDE_Exp_Complete_Ac_22134.pride.mgf.gz",
  "preferred_download_url": "https://ftp.pride.ebi.ac.uk/pride/data/archive/2012/03/PXD000001/generated/PRIDE_Exp_Complete_Ac_22134.pride.mgf.gz",
  "public_locations": [
    {
      "normalized_url": null,
      "protocol": "Aspera Protocol",
      "url": "prd_ascp@fasp.ebi.ac.uk:pride/data/archive/2012/03/PXD000001/generated/PRIDE_Exp_Complete_Ac_22134.pride.mgf.gz"
    },
    {
      "normalized_url": "https://ftp.pride.ebi.ac.uk/pride/data/archive/2012/03/PXD000001/generated/PRIDE_Exp_Complete_Ac_22134.pride.mgf.gz",
      "protocol": "FTP Protocol",
      "url": "ftp://ftp.pride.ebi.ac.uk/pride/data/archive/2012/03/PXD000001/generated/PRIDE_Exp_Complete_Ac_22134.pride.mgf.gz"
    }
  ],
  "publication_date": "2012-03-07T00:00:00.000+00:00",
  "repository_size_bytes": 16448103,
  "repository_size_kind": "repository_reported",
  "schema_version": 1,
  "source": "PRIDE",
  "submission_date": "2012-03-13T00:00:00.000+00:00",
  "updated_date": "2017-06-20T14:57:06.000+00:00",
  "variants": []
}
